icss_feature_selection/__init__.py
icss_feature_selection/selector.py
icss_feature_selection-0.1.4.dist-info/licenses/LICENSE
icss_feature_selection-0.1.4.dist-info/METADATA
icss_feature_selection-0.1.4.dist-info/WHEEL
icss_feature_selection-0.1.4.dist-info/top_level.txt
icss_feature_selection-0.1.4.dist-info/RECORD
