Metadata-Version: 2.4
Name: icss-feature-selection
Version: 0.1.4
Summary: A scikit-learn compatible feature selector using the Interval Chi-Square Score (ICSS) algorithm.
Author-email: Vinay Kumar N <vinaykumar.natraj@gmail.com>
License:                                  Apache License
Project-URL: Homepage, https://github.com/vinaykumarngitub/icss-feature-selection
Project-URL: Issues, https://github.com/vinaykumarngitub/icss-feature-selection/issues
Keywords: feature selection,scikit-learn,chi-square,interval data,machine learning
Classifier: Programming Language :: Python :: 3
Classifier: License :: OSI Approved :: Apache Software License
Classifier: Operating System :: OS Independent
Classifier: Intended Audience :: Science/Research
Classifier: Topic :: Scientific/Engineering :: Information Analysis
Requires-Python: >=3.8
License-File: LICENSE
Requires-Dist: numpy
Requires-Dist: scikit-learn
Dynamic: license-file
